pypomp/LG.py
pypomp/__init__.py
pypomp/dacca.py
pypomp/internal_functions.py
pypomp/mif.py
pypomp/model_struct.py
pypomp/mop.py
pypomp/panelPomp_class.py
pypomp/pfilter.py
pypomp/pfilter_complete.py
pypomp/pomp_class.py
pypomp/simulate.py
pypomp/spx.py
pypomp/train.py
pypomp/util.py
pypomp/data/Mesocosmdata.xls
pypomp/data/SPX.csv
pypomp/data/dacca/cholera-mif1-mif2.rda
pypomp/data/dacca/cholera.csv
pypomp/data/dacca/covars.csv
pypomp/data/dacca/covart.csv
pypomp/data/dacca/dacca.csv
pypomp/data/dacca/fit1.csv
pypomp/data/dacca/ll_pomp.csv
pypomp/data/dacca/ll_pomp_sd_0.csv
pypomp/data/dacca/pfs.csv
pypomp/data/dacca/pfs0.csv
pypomp/data/uk_measles/uk_measles.pkl
pypomp/data/uk_measles/uk_measles.py
pypomp/data/uk_measles/raw/births_rural.csv
pypomp/data/uk_measles/raw/births_urban.csv
pypomp/data/uk_measles/raw/coord_rural.csv
pypomp/data/uk_measles/raw/coord_urban.csv
pypomp/data/uk_measles/raw/measles_rural.csv
pypomp/data/uk_measles/raw/measles_urban.csv
pypomp/data/uk_measles/raw/pop_rural.csv
pypomp/data/uk_measles/raw/pop_urban.csv
pypomp/measles/measlesPomp.py
pypomp/measles/model_001b.py
pypomp-0.1.4.dist-info/METADATA
pypomp-0.1.4.dist-info/WHEEL
pypomp-0.1.4.dist-info/licenses/LICENSE
pypomp-0.1.4.dist-info/RECORD
