Metadata-Version: 2.4
Name: pypomp
Version: 0.1.4
Summary: Modeling and inference using partially observed Markov process (POMP) models
Project-URL: Homepage, https://github.com/pypomp/pypomp
Project-URL: Issues, https://github.com/pypomp/pypomp/issues
Author-email: The pypomp core developer team <pypomp-org@umich.edu>
License-File: LICENSE
Classifier: License :: OSI Approved :: MIT License
Classifier: Operating System :: OS Independent
Classifier: Programming Language :: Python :: 3
Requires-Python: >=3.10
Requires-Dist: jax>=0.4.31
Requires-Dist: matplotlib
Requires-Dist: numpy>=1.24
Requires-Dist: pandas
Requires-Dist: scipy
Requires-Dist: seaborn
Requires-Dist: tqdm>=4.66.4
Requires-Dist: typing-extensions
Requires-Dist: xarray
